[{"country_code":"BM","state_code":"01","province_code":"","name":"Devonshire","cp":["DV 01","DV 02","DV 03","DV 04","DV 05","DV 06","DV 07","DV 08","FL 01","FL 02","FL 03","FL 05","HM 14","HM 15","HM 16","HM 18","HM 19","HM 20"],"lat":"32.3028","lng":"-64.7558"},{"country_code":"BM","state_code":"02","province_code":"","name":"Hamilton Parish","cp":["CR 01","CR 02","CR 03","CR 04","FL 04","HS 02"],"lat":"32.3264","lng":"-64.7411"},{"country_code":"BM","state_code":"03","province_code":"","name":"City of Hamilton","cp":["HM 08","HM 09","HM 10","HM 11","HM 12","HM 17","HM 19"],"lat":"32.2949","lng":"-64.783"},{"country_code":"BM","state_code":"04","province_code":"","name":"Paget","cp":["DV 03","DV 04","PG 01","PG 02","PG 03","PG 04","PG 05","PG 06"],"lat":"32.2783","lng":"-64.7817"},{"country_code":"BM","state_code":"05","province_code":"","name":"Pembroke","cp":["HM 01","HM 02","HM 03","HM 04","HM 05","HM 06","HM 07","HM 08","HM 09","HM 13","HM 14","HM 15","HM 16","HM 17","HM 18","HM 19","HM 20"],"lat":"32.3002","lng":"-64.792"},{"country_code":"BM","state_code":"06","province_code":"","name":"Town of St. George","cp":["GE 02","GE 03","GE 04","GE 05"],"lat":"32.3842","lng":"-64.6764"},{"country_code":"BM","state_code":"06","province_code":"","name":"St. George","cp":["HS 02"],"lat":"32.3817","lng":"-64.6781"},{"country_code":"BM","state_code":"07","province_code":"","name":"St. George's","cp":["CR 04","DD 01","DD 02","DD 03","GE 01","GE 02","GE 03","GE 04","GE 05","GE CX","HS 02"],"lat":"32.3264","lng":"-64.7411"},{"country_code":"BM","state_code":"08","province_code":"","name":"Sandys","cp":["MA 01","MA 02","MA 03","MA 04","MA 05","MA 06","SB 01","SB 02","SB 03"],"lat":"32.2934","lng":"-64.8683"},{"country_code":"BM","state_code":"09","province_code":"","name":"Smith\u2019s","cp":["FL 01","FL 02","FL 03","FL 04","FL 05","FL 06","FL 07","FL 08","HS 01","HS 02"],"lat":"32.3264","lng":"-64.7411"},{"country_code":"BM","state_code":"10","province_code":"","name":"Southampton","cp":["SB 02","SB 03","SB 04","SN 01","SN 02","SN 03","SN 04","WK 01","WK 03"],"lat":"32.2508","lng":"-64.8564"},{"country_code":"BM","state_code":"11","province_code":"","name":"Warwick","cp":["PG 01","PG 04","WK 01","WK 02","WK 03","WK 04","WK 05","WK 06","WK 07","WK 08","WK 09","WK 10"],"lat":"32.2658","lng":"-64.8072"}]