[{"code":"BB","country_code":"BI","state_code":"","name":"Bubanza","geo":{"center":{"lat":-3.083333,"lng":29.4},"min":{"lat":-3.083333,"lng":29.4},"max":{"lat":-3.083333,"lng":29.4}}},{"code":"BJ","country_code":"BI","state_code":"","name":"Bujumbura","geo":{"center":{"lat":-3.383333,"lng":29.366667},"min":{"lat":-3.383333,"lng":29.366667},"max":{"lat":-3.383333,"lng":29.366667}}},{"code":"BR","country_code":"BI","state_code":"","name":"Bururi","geo":{"center":{"lat":-3.95,"lng":29.616667},"min":{"lat":-3.95,"lng":29.616667},"max":{"lat":-3.95,"lng":29.616667}}},{"code":"CA","country_code":"BI","state_code":"","name":"Cankuzo","geo":{"center":{"lat":-3.2196819,"lng":30.5466187},"min":{"lat":-3.2196819,"lng":30.5466187},"max":{"lat":-3.2196819,"lng":30.5466187}}},{"code":"CI","country_code":"BI","state_code":"","name":"Cibitoke","geo":{"center":{"lat":-2.888611,"lng":29.12},"min":{"lat":-2.888611,"lng":29.12},"max":{"lat":-2.888611,"lng":29.12}}},{"code":"GI","country_code":"BI","state_code":"","name":"Gitega","geo":{"center":{"lat":-3.428803,"lng":29.924903},"min":{"lat":-3.428803,"lng":29.924903},"max":{"lat":-3.428803,"lng":29.924903}}},{"code":"KI","country_code":"BI","state_code":"","name":"Kirundo","geo":{"center":{"lat":-2.5848378,"lng":30.0961296},"min":{"lat":-2.5848378,"lng":30.0961296},"max":{"lat":-2.5848378,"lng":30.0961296}}},{"code":"KR","country_code":"BI","state_code":"","name":"Karuzi","geo":{"center":{"lat":-3.1,"lng":30.166667},"min":{"lat":-3.1,"lng":30.166667},"max":{"lat":-3.1,"lng":30.166667}}},{"code":"KY","country_code":"BI","state_code":"","name":"Kayanza","geo":{"center":{"lat":-2.9218531,"lng":29.6252858},"min":{"lat":-2.9218531,"lng":29.6252858},"max":{"lat":-2.9218531,"lng":29.6252858}}},{"code":"MA","country_code":"BI","state_code":"","name":"Makamba","geo":{"center":{"lat":-4.133333,"lng":29.8},"min":{"lat":-4.133333,"lng":29.8},"max":{"lat":-4.133333,"lng":29.8}}},{"code":"MU","country_code":"BI","state_code":"","name":"Muramvya","geo":{"center":{"lat":-3.2675245,"lng":29.6223878},"min":{"lat":-3.2675245,"lng":29.6223878},"max":{"lat":-3.2675245,"lng":29.6223878}}},{"code":"MW","country_code":"BI","state_code":"","name":"Mwaro","geo":{"center":{"lat":-3.511985,"lng":29.6991642},"min":{"lat":-3.511985,"lng":29.6991642},"max":{"lat":-3.511985,"lng":29.6991642}}},{"code":"MY","country_code":"BI","state_code":"","name":"Muyinga","geo":{"center":{"lat":-2.85,"lng":30.333333},"min":{"lat":-2.85,"lng":30.333333},"max":{"lat":-2.85,"lng":30.333333}}},{"code":"NG","country_code":"BI","state_code":"","name":"Ngozi","geo":{"center":{"lat":-2.9,"lng":29.833333},"min":{"lat":-2.9,"lng":29.833333},"max":{"lat":-2.9,"lng":29.833333}}},{"code":"RT","country_code":"BI","state_code":"","name":"Rutana","geo":{"center":{"lat":-3.9257199,"lng":29.9899512},"min":{"lat":-3.9257199,"lng":29.9899512},"max":{"lat":-3.9257199,"lng":29.9899512}}},{"code":"RY","country_code":"BI","state_code":"","name":"Ruyigi","geo":{"center":{"lat":-3.4750027,"lng":30.2483881},"min":{"lat":-3.4750027,"lng":30.2483881},"max":{"lat":-3.4750027,"lng":30.2483881}}}]