[{"code":1,"country_code":"GA","state_code":"","name":"Estuaire","geo":{"center":{"lat":0.4432864,"lng":10.0807298},"min":{"lat":0.4432864,"lng":10.0807298},"max":{"lat":0.4432864,"lng":10.0807298}}},{"code":2,"country_code":"GA","state_code":"","name":"Haut-Ogoou\u00e9","geo":{"center":{"lat":-1.4762544,"lng":13.914399},"min":{"lat":-1.4762544,"lng":13.914399},"max":{"lat":-1.4762544,"lng":13.914399}}},{"code":3,"country_code":"GA","state_code":"","name":"Moyen-Ogoou\u00e9","geo":{"center":{"lat":-0.442784,"lng":10.439656},"min":{"lat":-0.442784,"lng":10.439656},"max":{"lat":-0.442784,"lng":10.439656}}},{"code":4,"country_code":"GA","state_code":"","name":"Ngouni\u00e9","geo":{"center":{"lat":-1.4930303,"lng":10.9807003},"min":{"lat":-1.4930303,"lng":10.9807003},"max":{"lat":-1.4930303,"lng":10.9807003}}},{"code":5,"country_code":"GA","state_code":"","name":"Nyanga","geo":{"center":{"lat":-2.8821033,"lng":11.1617356},"min":{"lat":-2.8821033,"lng":11.1617356},"max":{"lat":-2.8821033,"lng":11.1617356}}},{"code":6,"country_code":"GA","state_code":"","name":"Ogoou\u00e9-Ivindo","geo":{"center":{"lat":0.8818311,"lng":13.1740348},"min":{"lat":0.8818311,"lng":13.1740348},"max":{"lat":0.8818311,"lng":13.1740348}}},{"code":7,"country_code":"GA","state_code":"","name":"Ogoou\u00e9-Lolo","geo":{"center":{"lat":-0.8844093,"lng":12.4380581},"min":{"lat":-0.8844093,"lng":12.4380581},"max":{"lat":-0.8844093,"lng":12.4380581}}},{"code":8,"country_code":"GA","state_code":"","name":"Ogoou\u00e9-Maritime","geo":{"center":{"lat":-1.3465975,"lng":9.7232673},"min":{"lat":-1.3465975,"lng":9.7232673},"max":{"lat":-1.3465975,"lng":9.7232673}}},{"code":9,"country_code":"GA","state_code":"","name":"Woleu-Ntem","geo":{"center":{"lat":1.4892408,"lng":11.7068294},"min":{"lat":1.4892408,"lng":11.7068294},"max":{"lat":1.4892408,"lng":11.7068294}}}]