[{"code":"AH","country_code":"KW","state_code":"","name":"Al Ahmadi","geo":{"center":{"lat":29.083333,"lng":48.083333},"min":{"lat":29.083333,"lng":48.083333},"max":{"lat":29.083333,"lng":48.083333}}},{"code":"FA","country_code":"KW","state_code":"","name":"Al Farwaniyah","geo":{"center":{"lat":29.2428445,"lng":47.9416114},"min":{"lat":29.2428445,"lng":47.9416114},"max":{"lat":29.2428445,"lng":47.9416114}}},{"code":"HA","country_code":"KW","state_code":"","name":"Hawalli","geo":{"center":{"lat":29.333,"lng":48.029},"min":{"lat":29.333,"lng":48.029},"max":{"lat":29.333,"lng":48.029}}},{"code":"JA","country_code":"KW","state_code":"","name":"Al Jahrah","geo":{"center":{"lat":29.3365728,"lng":47.6755291},"min":{"lat":29.3365728,"lng":47.6755291},"max":{"lat":29.3365728,"lng":47.6755291}}},{"code":"KU","country_code":"KW","state_code":"","name":"Al Kuwayt","geo":{"center":{"lat":29.375859,"lng":47.9774052},"min":{"lat":29.375859,"lng":47.9774052},"max":{"lat":29.375859,"lng":47.9774052}}},{"code":"MU","country_code":"KW","state_code":"","name":"Mubarak al-Kabir","geo":{"center":{"lat":29.21224,"lng":48.0605108},"min":{"lat":29.21224,"lng":48.0605108},"max":{"lat":29.21224,"lng":48.0605108}}}]