[{"code":"00","country_code":"RS","state_code":"","name":"Belgrade","geo":{"center":{"lat":44.786568,"lng":20.4489216},"min":{"lat":44.786568,"lng":20.4489216},"max":{"lat":44.786568,"lng":20.4489216}}},{"code":"01","country_code":"RS","state_code":"","name":"Severna Backa","geo":{"center":{"lat":45.9803394,"lng":19.5907},"min":{"lat":45.9803394,"lng":19.5907},"max":{"lat":45.9803394,"lng":19.5907}}},{"code":"02","country_code":"RS","state_code":"","name":"Srednji Banat","geo":{"center":{"lat":45.4788485,"lng":20.6082522},"min":{"lat":45.4788485,"lng":20.6082522},"max":{"lat":45.4788485,"lng":20.6082522}}},{"code":"03","country_code":"RS","state_code":"","name":"Severni Banat","geo":{"center":{"lat":45.906839,"lng":19.9993417},"min":{"lat":45.906839,"lng":19.9993417},"max":{"lat":45.906839,"lng":19.9993417}}},{"code":"04","country_code":"RS","state_code":"","name":"Ju\u017eni Banat","geo":{"center":{"lat":45.0027457,"lng":21.0542509},"min":{"lat":45.0027457,"lng":21.0542509},"max":{"lat":45.0027457,"lng":21.0542509}}},{"code":"05","country_code":"RS","state_code":"","name":"Zapadna Backa","geo":{"center":{"lat":45.7355385,"lng":19.1897364},"min":{"lat":45.7355385,"lng":19.1897364},"max":{"lat":45.7355385,"lng":19.1897364}}},{"code":"06","country_code":"RS","state_code":"","name":"Ju\u017ena Backa","geo":{"center":{"lat":45.4890344,"lng":19.6976187},"min":{"lat":45.4890344,"lng":19.6976187},"max":{"lat":45.4890344,"lng":19.6976187}}},{"code":"07","country_code":"RS","state_code":"","name":"Srem","geo":{"center":{"lat":45.0029171,"lng":19.8013773},"min":{"lat":45.0029171,"lng":19.8013773},"max":{"lat":45.0029171,"lng":19.8013773}}},{"code":"08","country_code":"RS","state_code":"","name":"Macva","geo":{"center":{"lat":44.5925314,"lng":19.5082246},"min":{"lat":44.5925314,"lng":19.5082246},"max":{"lat":44.5925314,"lng":19.5082246}}},{"code":"09","country_code":"RS","state_code":"","name":"Kolubara","geo":{"center":{"lat":44.2674361,"lng":19.8980841},"min":{"lat":44.2674361,"lng":19.8980841},"max":{"lat":44.2674361,"lng":19.8980841}}},{"code":10,"country_code":"RS","state_code":"","name":"Podunavlje","geo":{"center":{"lat":44.4729156,"lng":20.9901426},"min":{"lat":44.4729156,"lng":20.9901426},"max":{"lat":44.4729156,"lng":20.9901426}}},{"code":11,"country_code":"RS","state_code":"","name":"Branicevo","geo":{"center":{"lat":44.705,"lng":21.538333},"min":{"lat":44.705,"lng":21.538333},"max":{"lat":44.705,"lng":21.538333}}},{"code":12,"country_code":"RS","state_code":"","name":"\u0160umadija","geo":{"center":{"lat":44.2050678,"lng":20.7856565},"min":{"lat":44.2050678,"lng":20.7856565},"max":{"lat":44.2050678,"lng":20.7856565}}},{"code":13,"country_code":"RS","state_code":"","name":"Pomoravlje","geo":{"center":{"lat":43.9591379,"lng":21.271353},"min":{"lat":43.9591379,"lng":21.271353},"max":{"lat":43.9591379,"lng":21.271353}}},{"code":14,"country_code":"RS","state_code":"","name":"Bor","geo":{"center":{"lat":44.0698918,"lng":22.0985086},"min":{"lat":44.0698918,"lng":22.0985086},"max":{"lat":44.0698918,"lng":22.0985086}}},{"code":15,"country_code":"RS","state_code":"","name":"Zajecar","geo":{"center":{"lat":43.9015048,"lng":22.2738011},"min":{"lat":43.9015048,"lng":22.2738011},"max":{"lat":43.9015048,"lng":22.2738011}}},{"code":16,"country_code":"RS","state_code":"","name":"Zlatibor","geo":{"center":{"lat":43.6554553,"lng":19.6633226},"min":{"lat":43.6554553,"lng":19.6633226},"max":{"lat":43.6554553,"lng":19.6633226}}},{"code":17,"country_code":"RS","state_code":"","name":"Moravica","geo":{"center":{"lat":43.5393662,"lng":21.7117215},"min":{"lat":43.5393662,"lng":21.7117215},"max":{"lat":43.5393662,"lng":21.7117215}}},{"code":18,"country_code":"RS","state_code":"","name":"Ra\u0161ka","geo":{"center":{"lat":43.291944,"lng":20.615556},"min":{"lat":43.291944,"lng":20.615556},"max":{"lat":43.291944,"lng":20.615556}}},{"code":19,"country_code":"RS","state_code":"","name":"Rasina","geo":{"center":{"lat":43.5789182,"lng":21.3484472},"min":{"lat":43.5789182,"lng":21.3484472},"max":{"lat":43.5789182,"lng":21.3484472}}},{"code":20,"country_code":"RS","state_code":"","name":"Ni\u0161ava","geo":{"center":{"lat":43.3738902,"lng":21.9322331},"min":{"lat":43.3738902,"lng":21.9322331},"max":{"lat":43.3738902,"lng":21.9322331}}},{"code":21,"country_code":"RS","state_code":"","name":"Toplica","geo":{"center":{"lat":43.1906592,"lng":21.3407762},"min":{"lat":43.1906592,"lng":21.3407762},"max":{"lat":43.1906592,"lng":21.3407762}}},{"code":22,"country_code":"RS","state_code":"","name":"Pirot","geo":{"center":{"lat":43.1557012,"lng":22.5856812},"min":{"lat":43.1557012,"lng":22.5856812},"max":{"lat":43.1557012,"lng":22.5856812}}},{"code":23,"country_code":"RS","state_code":"","name":"Jablanica","geo":{"center":{"lat":43.443889,"lng":21.271389},"min":{"lat":43.443889,"lng":21.271389},"max":{"lat":43.443889,"lng":21.271389}}},{"code":24,"country_code":"RS","state_code":"","name":"Pcinja","geo":{"center":{"lat":42.5836362,"lng":22.1430215},"min":{"lat":42.5836362,"lng":22.1430215},"max":{"lat":42.5836362,"lng":22.1430215}}},{"code":25,"country_code":"RS","state_code":"","name":"Kosovo","geo":{"center":{"lat":44.016521,"lng":21.005859},"min":{"lat":44.016521,"lng":21.005859},"max":{"lat":44.016521,"lng":21.005859}}},{"code":26,"country_code":"RS","state_code":"","name":"Pec\u00b4","geo":{"center":{"lat":43.5725,"lng":19.8797222},"min":{"lat":43.5725,"lng":19.8797222},"max":{"lat":43.5725,"lng":19.8797222}}},{"code":27,"country_code":"RS","state_code":"","name":"Prizren","geo":{"center":{"lat":43.6930556,"lng":19.28},"min":{"lat":43.6930556,"lng":19.28},"max":{"lat":43.6930556,"lng":19.28}}},{"code":28,"country_code":"RS","state_code":"","name":"Kosovska Mitrovica","geo":{"center":{"lat":44.9980615,"lng":19.8087171},"min":{"lat":44.9980615,"lng":19.8087171},"max":{"lat":44.9980615,"lng":19.8087171}}},{"code":29,"country_code":"RS","state_code":"","name":"Kosovo-Pomoravlje","geo":{"center":{"lat":null,"lng":null},"min":{"lat":null,"lng":null},"max":{"lat":null,"lng":null}}}]