[{"code":"FUN","country_code":"TV","state_code":"","name":"Funafuti","geo":{"center":{"lat":-8.516667,"lng":179.216667},"min":{"lat":-8.516667,"lng":179.216667},"max":{"lat":-8.516667,"lng":179.216667}}},{"code":"NIT","country_code":"TV","state_code":"","name":"Niutao","geo":{"center":{"lat":-6.1064258,"lng":177.3438429},"min":{"lat":-6.1064258,"lng":177.3438429},"max":{"lat":-6.1064258,"lng":177.3438429}}},{"code":"NIU","country_code":"TV","state_code":"","name":"Nui","geo":{"center":{"lat":-7.2426288,"lng":177.1485716},"min":{"lat":-7.2426288,"lng":177.1485716},"max":{"lat":-7.2426288,"lng":177.1485716}}},{"code":"NKF","country_code":"TV","state_code":"","name":"Nukufetau","geo":{"center":{"lat":-8,"lng":178.5},"min":{"lat":-8,"lng":178.5},"max":{"lat":-8,"lng":178.5}}},{"code":"NKL","country_code":"TV","state_code":"","name":"Nukulaelae","geo":{"center":{"lat":-9.381111,"lng":179.852222},"min":{"lat":-9.381111,"lng":179.852222},"max":{"lat":-9.381111,"lng":179.852222}}},{"code":"NMA","country_code":"TV","state_code":"","name":"Nanumea","geo":{"center":{"lat":-5.6815388,"lng":176.1281065},"min":{"lat":-5.6815388,"lng":176.1281065},"max":{"lat":-5.6815388,"lng":176.1281065}}},{"code":"NMG","country_code":"TV","state_code":"","name":"Nanumanga","geo":{"center":{"lat":-6.2910708,"lng":176.314856},"min":{"lat":-6.2910708,"lng":176.314856},"max":{"lat":-6.2910708,"lng":176.314856}}},{"code":"VAI","country_code":"TV","state_code":"","name":"Vaitupu","geo":{"center":{"lat":-7.4767327,"lng":178.6747675},"min":{"lat":-7.4767327,"lng":178.6747675},"max":{"lat":-7.4767327,"lng":178.6747675}}}]